pathvein/__init__.py
pathvein/_path_utils.py
pathvein/cli.py
pathvein/lib.py
pathvein/pattern.py
pathvein/py.typed
pathvein-0.9.0.dist-info/METADATA
pathvein-0.9.0.dist-info/WHEEL
pathvein-0.9.0.dist-info/entry_points.txt
pathvein-0.9.0.dist-info/licenses/LICENSE
pathvein-0.9.0.dist-info/RECORD
