Metadata-Version: 2.4
Name: pathvein
Version: 0.9.0
Summary: Rich and deep file structure pattern matching.
License-File: LICENSE
Requires-Python: >=3.8
Requires-Dist: typing-extensions>=4.12.2
Provides-Extra: cli
Requires-Dist: typer>=0.13.1; extra == 'cli'
Provides-Extra: s3
Requires-Dist: fsspec[s3]>=2024.10.0; extra == 's3'
Requires-Dist: universal-pathlib>=0.2.5; extra == 's3'
